factory_manager/__init__.py
factory_manager/factory_manager.py
factory_manager-0.1.0.dist-info/LICENSE
factory_manager-0.1.0.dist-info/METADATA
factory_manager-0.1.0.dist-info/WHEEL
factory_manager-0.1.0.dist-info/top_level.txt
factory_manager-0.1.0.dist-info/RECORD
