Metadata-Version: 2.1
Name: factory-manager
Version: 0.1.0
Summary: A package to create objects with their dependencies from descriptions in the form of a dictionary
Home-page: https://github.com/fab-bar/factory-manager
Author: Fabian Barteld
Author-email: fabian.barteld@rub.de
License: UNKNOWN
Platform: UNKNOWN
Classifier: Intended Audience :: Developers
Classifier: Development Status :: 4 - Beta
Classifier: License :: OSI Approved :: MIT License
Classifier: Programming Language :: Python :: 3
Requires-Python: >=3.6
Requires-Dist: typing-inspect
